board_game_scraper/__init__.py
board_game_scraper/__main__.py
board_game_scraper/__version__.py
board_game_scraper/cluster.py
board_game_scraper/download_bgg_dump.py
board_game_scraper/extensions.py
board_game_scraper/fields.yaml
board_game_scraper/full_merge.py
board_game_scraper/items.py
board_game_scraper/loaders.py
board_game_scraper/merge.py
board_game_scraper/middlewares.py
board_game_scraper/news.py
board_game_scraper/pipelines.py
board_game_scraper/prefixes.py
board_game_scraper/pubsub_pull.py
board_game_scraper/settings.py
board_game_scraper/split.py
board_game_scraper/utils.py
board_game_scraper/version_env.py
board_game_scraper/zip_rankings.py
board_game_scraper/spiders/__init__.py
board_game_scraper/spiders/bgg.py
board_game_scraper/spiders/bgg_geeklist.py
board_game_scraper/spiders/bgg_hotness.py
board_game_scraper/spiders/bgg_json_rankings.py
board_game_scraper/spiders/bgg_rankings.py
board_game_scraper/spiders/dbpedia.py
board_game_scraper/spiders/luding.py
board_game_scraper/spiders/spielen.py
board_game_scraper/spiders/wikidata.py
board_game_scraper-2.23.1.dist-info/LICENSE
board_game_scraper-2.23.1.dist-info/METADATA
board_game_scraper-2.23.1.dist-info/WHEEL
board_game_scraper-2.23.1.dist-info/entry_points.txt
board_game_scraper-2.23.1.dist-info/top_level.txt
board_game_scraper-2.23.1.dist-info/RECORD
