Metadata-Version: 2.1
Name: board-game-scraper
Version: 2.23.1
Summary: Board games data scraping and processing from BoardGameGeek and more!
Home-page: https://recommend.games/
Author: Markus Shepherd
Author-email: markus@recommend.games
License: MIT
Project-URL: Documentation, https://gitlab.com/recommend.games/board-game-scraper/blob/master/README.md
Project-URL: Funding, https://paypal.me/mschepke
Project-URL: Say Thanks!, https://saythanks.io/to/mk.schepke%40gmail.com
Project-URL: Source, https://gitlab.com/recommend.games/board-game-scraper
Project-URL: Tracker, https://gitlab.com/recommend.games/board-game-scraper/issues
Project-URL: Twitter, https://twitter.com/recommend_games
Keywords: board games,tabletop games,data,datasets,scraper,scrapy,spider,boardgamegeek,bgg,ludoj,ludoj-scraper
Classifier: Framework :: Scrapy
Classifier: License :: OSI Approved :: MIT License
Classifier: Programming Language :: Python
Classifier: Programming Language :: Python :: 3.7
Classifier: Programming Language :: Python :: 3.8
Classifier: Programming Language :: Python :: 3.9
Classifier: Programming Language :: Python :: 3.10
Classifier: Programming Language :: Python :: 3.11
Classifier: Topic :: Games/Entertainment :: Board Games
Requires-Python: >=3.7.0
License-File: LICENSE
Requires-Dist: awscli
Requires-Dist: boto
Requires-Dist: dedupe >=2.0.0
Requires-Dist: google-cloud-pubsub
Requires-Dist: itemadapter
Requires-Dist: jmespath
Requires-Dist: pillow
Requires-Dist: pympler
Requires-Dist: pyspark
Requires-Dist: python-dotenv
Requires-Dist: pytility[dates]
Requires-Dist: pytrie
Requires-Dist: pyyaml
Requires-Dist: requests
Requires-Dist: scrapy <2.1.0
Requires-Dist: scrapy-extensions[images] >=0.3.1
Requires-Dist: twisted
Requires-Dist: w3lib
Provides-Extra: cloud
Requires-Dist: smart-open >=1.8.1 ; extra == 'cloud'
Provides-Extra: git
Requires-Dist: gitpython ; extra == 'git'
